ai_org/__init__.py
ai_org/__version__.py
ai_org/cli.py
ai_org/commands/__init__.py
ai_org/commands/account.py
ai_org/commands/config.py
ai_org/commands/dns.py
ai_org/commands/ou.py
ai_org/commands/sso.py
ai_org/commands/stackset.py
ai_org/core/__init__.py
ai_org/core/account_factory.py
ai_org/core/account_manager.py
ai_org/core/aws_client.py
ai_org/core/config_manager.py
ai_org/core/ou_manager.py
ai_org/core/sso_manager.py
ai_org/core/stackset_manager.py
ai_org/utils/__init__.py
ai_org/utils/cache.py
ai_org/utils/config_loader.py
ai_org/utils/output.py
ai_org/utils/validators.py
augint_org-0.11.0.dist-info/METADATA
augint_org-0.11.0.dist-info/WHEEL
augint_org-0.11.0.dist-info/entry_points.txt
augint_org-0.11.0.dist-info/licenses/LICENSE
augint_org-0.11.0.dist-info/RECORD
