Metadata-Version: 2.4
Name: augint-org
Version: 0.11.0
Summary: CLI tool for managing AWS Organization accounts with Control Tower
Author-email: Samuel Vange <sam@augmentingintegrations.com>
License: Copyright (c) Augmenting Integrations LLC
License-File: LICENSE
Keywords: automation,aws,control-tower,organizations,sso
Classifier: Development Status :: 3 - Alpha
Classifier: Intended Audience :: System Administrators
Classifier: License :: OSI Approved :: MIT License
Classifier: Programming Language :: Python :: 3
Classifier: Programming Language :: Python :: 3.9
Classifier: Programming Language :: Python :: 3.10
Classifier: Programming Language :: Python :: 3.11
Classifier: Topic :: System :: Systems Administration
Requires-Python: >=3.12
Requires-Dist: boto3>=1.34
Requires-Dist: click>=8.1
Requires-Dist: python-dotenv>=1.0
Requires-Dist: pyyaml>=6.0
Requires-Dist: rich>=13.7
